{
  "placeholder_id": "generated",
  "canvas": {
    "width": 1080,
    "height": 330
  },
  "layout": "single",
  "panels": [
    {
      "id": "1"
    }
  ],
  "nodes": [],
  "edges": [],
  "groups": [],
  "arrows": [],
  "labels": [],
  "titles": [
    {
      "id": "t1",
      "text": "Speed Comparison",
      "x": 50,
      "y": 15,
      "color": "#FAFF00",
      "boundingBox": "c1"
    }
  ],
  "captions": [],
  "containers": [
    {
      "id": "c1",
      "x": 15,
      "y": 30,
      "width": 70,
      "height": 55,
      "subdivided": false,
      "panel": "1",
      "table": {
        "columns": 2,
        "rows": 4,
        "headerColor": "#014063"
      }
    }
  ],
  "dashedLines": [],
  "spec": {
    "description": "",
    "purpose": "",
    "composition": "",
    "topology": ""
  }
}